data_utils/annotate_mgfs.py
data_utils/feature_extractor.py
depthcharge/__init__.py
depthcharge/masses.py
depthcharge/similarity.py
depthcharge/utils.py
depthcharge/version.py
depthcharge/__pycache__/__init__.cpython-310.pyc
depthcharge/__pycache__/masses.cpython-310.pyc
depthcharge/__pycache__/similarity.cpython-310.pyc
depthcharge/__pycache__/utils.cpython-310.pyc
depthcharge/__pycache__/version.cpython-310.pyc
depthcharge/components/__init__.py
depthcharge/components/attentions.py
depthcharge/components/encoders.py
depthcharge/components/feedforward.py
depthcharge/components/mixins.py
depthcharge/components/transformers.py
depthcharge/components/__pycache__/__init__.cpython-310.pyc
depthcharge/components/__pycache__/encoders.cpython-310.pyc
depthcharge/components/__pycache__/feedforward.cpython-310.pyc
depthcharge/components/__pycache__/mixins.cpython-310.pyc
depthcharge/components/__pycache__/transformers.cpython-310.pyc
depthcharge/data/__init__.py
depthcharge/data/datasets.py
depthcharge/data/dia_config.py
depthcharge/data/dia_io.py
depthcharge/data/hdf5.py
depthcharge/data/loaders.py
depthcharge/data/parsers.py
depthcharge/data/preprocessing.py
depthcharge/data/__pycache__/__init__.cpython-310.pyc
depthcharge/data/__pycache__/datasets.cpython-310.pyc
depthcharge/data/__pycache__/dia_io.cpython-310.pyc
depthcharge/data/__pycache__/hdf5.cpython-310.pyc
depthcharge/data/__pycache__/loaders.cpython-310.pyc
depthcharge/data/__pycache__/parsers.cpython-310.pyc
depthcharge/data/__pycache__/preprocessing.cpython-310.pyc
depthcharge/models/__init__.py
depthcharge/models/__pycache__/__init__.cpython-310.pyc
depthcharge/models/denovo/__init__.py
depthcharge/models/denovo/model.py
depthcharge/models/denovo/__pycache__/__init__.cpython-310.pyc
depthcharge/models/denovo/__pycache__/model.cpython-310.pyc
transdia-0.0.8.dist-info/licenses/LICENSE
transformer_dia/__init__.py
transformer_dia/config.yaml
transformer_dia/transformer_dia.py
transformer_dia/utils.py
transformer_dia/version.py
transdia-0.0.8.dist-info/METADATA
transdia-0.0.8.dist-info/WHEEL
transdia-0.0.8.dist-info/entry_points.txt
transdia-0.0.8.dist-info/top_level.txt
transdia-0.0.8.dist-info/RECORD
